better_bing_image_downloader/__init__.py
better_bing_image_downloader/bing.py
better_bing_image_downloader/crawler.py
better_bing_image_downloader/download.py
better_bing_image_downloader/helperdownload.py
better_bing_image_downloader/multidownloader.py
better_bing_image_downloader/utils.py
better_bing_image_downloader-2.0.0.dist-info/licenses/LICENSE
better_bing_image_downloader-2.0.0.dist-info/METADATA
better_bing_image_downloader-2.0.0.dist-info/WHEEL
better_bing_image_downloader-2.0.0.dist-info/top_level.txt
better_bing_image_downloader-2.0.0.dist-info/RECORD
