Metadata-Version: 2.4
Name: better_bing_image_downloader
Version: 2.0.0
Summary: This package is built on top of bing-image-downloader by gaurav singh
Home-page: https://github.com/KTS-o7/better_bing_image_downloader
Author: Krishnatejaswi S
Author-email: shentharkrishnatejaswi@gmail.com
Keywords: bing,images,scraping,image download,bulk image downloader
Classifier: Programming Language :: Python :: 3
Classifier: License :: OSI Approved :: MIT License
Classifier: Operating System :: OS Independent
License-File: LICENSE
Dynamic: author
Dynamic: author-email
Dynamic: classifier
Dynamic: description
Dynamic: description-content-type
Dynamic: home-page
Dynamic: keywords
Dynamic: license-file
Dynamic: summary
